Workbook
Name GrowthRate: Assumptions!$B$3
Name SalesData: Data!$A$1:$F$12

Sheet Data
A1: Region | B1: Product | C1: Qty | D1: OrderDate | E1: Price | F1: Revenue
A2: East | B2: Widget | C2: 3 | D2: 45292 | E2: 10 | F2: =tbl_Sales[[#This Row],[Qty]]*tbl_Sales[[#This Row],[Price]] -> 30
A3: east | B3: Widget | C3: 2 | D3: 45323 | E3: 10 | F3: =tbl_Sales[[#This Row],[Qty]]*tbl_Sales[[#This Row],[Price]] -> 20
A4: West | B4: Gadget | C4: 5 | D4: 45352 | E4: 20.5 | F4: =tbl_Sales[[#This Row],[Qty]]*tbl_Sales[[#This Row],[Price]] -> 102.5
A5: West | B5: Gadget | C5: 1 | D5: 45383 | E5: 20.5 | F5: =tbl_Sales[[#This Row],[Qty]]*tbl_Sales[[#This Row],[Price]] -> 20.5
A6: North | B6: Widget | C6: 4 | D6: 45413 | E6: 10 | F6: =tbl_Sales[[#This Row],[Qty]]*tbl_Sales[[#This Row],[Price]] -> 40
B7: Gadget | C7: 2 | D7: 45444 | E7: 20.5 | F7: =tbl_Sales[[#This Row],[Qty]]*tbl_Sales[[#This Row],[Price]] -> 41
A8: East | B8: Gizmo | C8: 1 | D8: 2024-07-15 | E8: 7.25 | F8: =tbl_Sales[[#This Row],[Qty]]*tbl_Sales[[#This Row],[Price]] -> 7.25
A9: East | B9: Widget | D9: 45505 | E9: 10 | F9: =tbl_Sales[[#This Row],[Qty]]*tbl_Sales[[#This Row],[Price]] -> 0
A10: West | B10: Widget | C10: 6 | D10: 60 | E10: 10 | F10: =tbl_Sales[[#This Row],[Qty]]*tbl_Sales[[#This Row],[Price]] -> 60
A11: North | B11: Gizmo | C11: 2 | D11: 45566 | E11: 7.25 | F11: =tbl_Sales[[#This Row],[Qty]]*tbl_Sales[[#This Row],[Price]] -> 14.5
A12: EAST | B12: Gadget | C12: 1 | D12: 45597 | E12: 20.5 | F12: =tbl_Sales[[#This Row],[Qty]]*tbl_Sales[[#This Row],[Price]] -> 20.5
A13: Total | F13: =SUBTOTAL(109,tbl_Sales[Revenue]) -> 356.25

Sheet Ledger
A1: Group | B1: Entry | C1: Amounts
C2: Debit | D2: Credit
A3: Ops | B3: Rent | C3: 1000 | D3: 0
A4: Ops | B4: Power | C4: 250 | D4: 0
A5: Ops | B5: Refund | C5: 0 | D5: 100
A6: Ops Subtotal | C6: =SUBTOTAL(9,C3:C5) -> 1250 | D6: =SUBTOTAL(9,D3:D5) -> 100
A7: Sales | B7: Alpha | C7: 0 | D7: 700
A8: Sales | B8: Beta | C8: 0 | D8: 400
A9: Sales | B9: Gamma | C9: 0 | D9: 150
A10: Sales Subtotal | C10: =SUBTOTAL(9,C7:C9) -> 0 | D10: =SUBTOTAL(9,D7:D9) -> 1250

Sheet Lookup
A1: Threshold | B1: Rate | D1: Threshold | E1: Rate | G1: Test | H1: Result | J1: Key | K1: Code
A2: 0 | B2: 0 | D2: 500 | E2: 0.1 | G2: VLOOKUP TRUE, sorted bracket | H2: =VLOOKUP(750,A2:B6,2,TRUE) -> 0.1 | J2: East | K2: 1
A3: 100 | B3: 0.05 | D3: 0 | E3: 0 | G3: VLOOKUP TRUE, unsorted copy (garbage) | H3: =VLOOKUP(750,D2:E6,2,TRUE) -> 0 | J3: West | K3: 2
A4: 500 | B4: 0.1 | D4: 5000 | E4: 0.2 | G4: VLOOKUP exact, no match | H4: =VLOOKUP(750,A2:B6,2,FALSE) -> #N/A | J4: North | K4: 3
A5: 1000 | B5: 0.15 | D5: 100 | E5: 0.05 | G5: IFERROR around the no match | H5: =IFERROR(VLOOKUP(750,A2:B6,2,FALSE),0) -> 0
A6: 5000 | B6: 0.2 | D6: 1000 | E6: 0.15 | G6: VLOOKUP TRUE below the first key | H6: =VLOOKUP(-5,A2:B6,2,TRUE) -> #N/A
G7: MATCH, 3rd arg omitted, sorted | H7: =MATCH(750,A2:A6) -> 3
G8: MATCH, 3rd arg omitted, unsorted | H8: =MATCH(750,D2:D6) -> 2
G9: VLOOKUP exact, text key in another case | H9: =VLOOKUP("east",J2:K4,2,FALSE) -> 1
G10: MATCH exact, text key in another case | H10: =MATCH("EAST",J2:J4,0) -> 1

Sheet Report
A1: 1 | C1: min Qty (A1) | D1: 3 | E1: min Qty, context 2 (D1) | G1: Month | H1: Units | I1: Doubled
B2: 45292 | C2: report start | D2: 45444 | E2: report start, context 2 (D2) | G2: 1 | H2: 10 | I2: =H2*2 -> 20
A3: SUMIFS region = east (case-insensitive) | B3: =SUMIFS(Data!$F$2:$F$12,Data!$A$2:$A$12,"east") -> 77.75 | D3: =SUMIFS(Data!$F$2:$F$12,Data!$A$2:$A$12,"WEST") -> 183 | E3: context 2: WEST, upper case | G3: 2 | H3: 20 | I3: =H3*2 -> 40
A4: SUMIFS Qty >= A1 | B4: =SUMIFS(Data!$F$2:$F$12,Data!$C$2:$C$12,">="&A1) -> 335.75 | D4: =SUMIFS(Data!$F$2:$F$12,Data!$C$2:$C$12,">="&D1) -> 232.5 | E4: context 2: >= D1 | G4: 3 | H4: 30 | I4: =H4*2 -> 60
A5: SUMIFS region wildcard *st | B5: =SUMIFS(Data!$F$2:$F$12,Data!$A$2:$A$12,"*st") -> 260.75 | D5: =SUMIFS(Data!$F$2:$F$12,Data!$A$2:$A$12,"N*") -> 54.5 | E5: context 2: N* | G5: 4 | H5: 40 | I5: =H5*2 -> 80
A6: SUMIFS blank region | B6: =SUMIFS(Data!$F$2:$F$12,Data!$A$2:$A$12,"") -> 41 | D6: =SUMIFS(Data!$F$2:$F$12,Data!$A$2:$A$12,"<>") -> 315.25 | E6: context 2: non-blank region | G6: 5 | H6: 50 | I6: 999
A7: AVERAGE Qty (skips text and blanks) | B7: =AVERAGE(Data!C2:C12) -> 2.8888889 | D7: =AVERAGEIFS(Data!$C$2:$C$12,Data!$A$2:$A$12,"west") -> 5.5 | E7: context 2: AVERAGEIFS west | G7: 6 | H7: 60 | I7: =H7*2 -> 120
A8: COUNT Qty | B8: =COUNT(Data!C2:C12) -> 9 | D8: =COUNTIFS(Data!$A$2:$A$12,"WEST",Data!$C$2:$C$12,">=0") -> 2 | E8: context 2: COUNTIFS west, numeric Qty | G8: 7 | H8: 70 | I8: =H8*2 -> 140
A9: COUNTA Qty | B9: =COUNTA(Data!C2:C12) -> 10 | D9: =COUNTIFS(Data!$A$2:$A$12,"west",Data!$C$2:$C$12,"<>") -> 3 | E9: context 2: COUNTIFS west, non-empty Qty | G9: 8 | H9: 80 | I9: =H9*2 -> 160
A10: COUNTIF Qty = 1 (matches text 1) | B10: =COUNTIF(Data!C:C,1) -> 3 | D10: =COUNTIF(Data!C:C,"2") -> 3 | E10: context 2: COUNTIF Qty = "2"
A11: COUNTIF region = east (case-insensitive) | B11: =COUNTIF(Data!A:A,"east") -> 5 | D11: =COUNTIF(Data!A:A,"NORTH") -> 2 | E11: context 2: COUNTIF region = "NORTH"
A12: SUM full column incl. total row (double count) | B12: =SUM(Data!F:F) -> 712.5 | D12: =SUMIFS(Data!F:F,Data!A:A,"west") -> 183 | E12: context 2: SUMIFS full column, west
A13: East plus tax (hardcoded 1.08) | B13: =B3*1.08 -> 83.97 | D13: =D3*1.08 -> 197.64 | E13: context 2: D3 plus tax (hardcoded 1.08)
A14: Days since report start (TODAY) | B14: =TODAY()-B2 -> 181 | D14: =TODAY()-D2 -> 29 | E14: context 2: Days since D2 (TODAY)
A15: SUMIFS OrderDate >= B2 (drops the text date and serial 60) | B15: =SUMIFS(Data!$F$2:$F$12,Data!$D$2:$D$12,">="&B2) -> 289 | D15: =SUMIFS(Data!$F$2:$F$12,Data!$D$2:$D$12,">="&D2) -> 76 | E15: context 2: SUMIFS OrderDate >= D2

Sheet Assumptions
A1: Assumption | B1: Value | D1: Growth sensitivity
A2: Opening balance | B2: 10000 | E2: =Forecast!F6 -> 12762.816
A3: Growth rate | B3: 0.05 | D3: 0.02 | E3: 11040.808
A4: Asset cost | B4: 12000 | D4: 0.04 | E4: 12166.529
A5: Salvage value | B5: 2000 | D5: 0.06 | E5: 13382.256
A6: Life (periods) | B6: 5 | D6: 0.08 | E6: 14693.281
A7: Interest rate | B7: 0.06
A10: Period | B10: 2025 | C10: 2026 | D10: 2027 | E10: 2028 | F10: 2029
A11: Flow | B11: 1000 | C11: 1200 | D11: 1500 | E11: 1800 | F11: 2000

Sheet Forecast
A1: Line | B1: 2025 | C1: 2026 | D1: 2027 | E1: 2028 | F1: 2029
A2: Opening | B2: =Assumptions!$B$2 -> 10000 | C2: =B5 -> 11649.485 | D2: =C5 -> 13607.185 | E2: =D5 -> 15995.258 | F2: =E5 -> 18840.325
A3: Flow | B3: =Assumptions!B11 -> 1000 | C3: =Assumptions!C11 -> 1200 | D3: =Assumptions!D11 -> 1500 | E3: =Assumptions!E11 -> 1800 | F3: =Assumptions!F11 -> 2000
A4: Interest (avg balance) | B4: =Assumptions!$B$7*AVERAGE(B2,B5) -> 649.48453 | C4: =Assumptions!$B$7*AVERAGE(C2,C5) -> 757.70006 | D4: =Assumptions!$B$7*AVERAGE(D2,D5) -> 888.07326 | E4: =Assumptions!$B$7*AVERAGE(E2,E5) -> 1045.0675 | F4: =Assumptions!$B$7*AVERAGE(F2,F5) -> 1227.2366
A5: Closing | B5: =B2+B3+B4 -> 11649.485 | C5: =C2+C3+C4 -> 13607.185 | D5: =D2+D3+D4 -> 15995.258 | E5: =E2+E3+E4 -> 18840.325 | F5: =F2+F3+F4 -> 22067.562
A6: Compounded | B6: =Assumptions!$B$2*(1+GrowthRate) -> 10500 | C6: =B6*(1+GrowthRate) -> 11025 | D6: =C6*(1+GrowthRate) -> 11576.25 | E6: =D6*(1+GrowthRate) -> 12155.062 | F6: =E6*(1+GrowthRate) -> 12762.816
A7: Depreciation | B7: =(Assumptions!$B$4-Assumptions!$B$5)/Assumptions!$B$6 -> 2000 | C7: =(Assumptions!$B$4-Assumptions!$B$5)/Assumptions!$B$6 -> 2000 | D7: =(Assumptions!$B$4-Assumptions!$B$5)/Assumptions!$B$6 -> 2000 | E7: =(Assumptions!$B$4-Assumptions!$B$5)/Assumptions!$B$6 -> 2000 | F7: =(Assumptions!$B$4-Assumptions!$B$5)/Assumptions!$B$6 -> 2000
A8: Net book value | B8: =Assumptions!$B$4-B7 -> 10000 | C8: =B8-C7 -> 8000 | D8: =C8-D7 -> 6000 | E8: =D8-E7 -> 4000 | F8: =E8-F7 -> 2000
A9: Cumulative flow | B9: =SUM($B$3:B3) -> 1000 | C9: =SUM($B$3:C3) -> 2200 | D9: =SUM($B$3:D3) -> 3700 | E9: =SUM($B$3:E3) -> 5500 | F9: =SUM($B$3:F3) -> 7500

Sheet MonteCarlo
A1: Draw | B1: Value | C1: Mean
A2: 1 | B2: =_xlfn.NORM.INV(RAND(),100,15) -> 103.52138 | C2: =AVERAGE(B2:B1001) -> 99.381849
A3: 2 | B3: =_xlfn.NORM.INV(RAND(),100,15) -> 97.144021
A4: 3 | B4: =_xlfn.NORM.INV(RAND(),100,15) -> 119.79011
A5: 4 | B5: =_xlfn.NORM.INV(RAND(),100,15) -> 69.391045
A6: 5 | B6: =_xlfn.NORM.INV(RAND(),100,15) -> 95.216346
A7: 6 | B7: =_xlfn.NORM.INV(RAND(),100,15) -> 118.40357
A8: 7 | B8: =_xlfn.NORM.INV(RAND(),100,15) -> 123.52614
A9: 8 | B9: =_xlfn.NORM.INV(RAND(),100,15) -> 85.066499
A10: 9 | B10: =_xlfn.NORM.INV(RAND(),100,15) -> 104.96235
A11: 10 | B11: =_xlfn.NORM.INV(RAND(),100,15) -> 104.23006
A12: 11 | B12: =_xlfn.NORM.INV(RAND(),100,15) -> 126.67406
A13: 12 | B13: =_xlfn.NORM.INV(RAND(),100,15) -> 85.056944
A14: 13 | B14: =_xlfn.NORM.INV(RAND(),100,15) -> 115.46929
... A1001: 1000 | B1001: =_xlfn.NORM.INV(RAND(),100,15) -> 103.09838

Sheet _Config
A1: Setting | B1: Value
A2: Password | B2: dummy-Passw0rd-not-real
A3: Environment | B3: fixture
